kedro_docker/__init__.py
kedro_docker/helpers.py
kedro_docker/plugin.py
kedro_docker/template/.dive-ci
kedro_docker/template/.dockerignore
kedro_docker/template/Dockerfile.simple
kedro_docker/template/Dockerfile.spark
kedro_docker-0.6.2.dist-info/METADATA
kedro_docker-0.6.2.dist-info/WHEEL
kedro_docker-0.6.2.dist-info/entry_points.txt
kedro_docker-0.6.2.dist-info/top_level.txt
kedro_docker-0.6.2.dist-info/RECORD
