Metadata-Version: 2.1
Name: kedro-docker
Version: 0.6.2
Summary: Kedro-Docker makes it easy to package Kedro projects with Docker.
Author: Kedro
License: Apache Software License (Apache 2.0)
Project-URL: Source, https://github.com/kedro-org/kedro-plugins/tree/main/kedro-docker
Project-URL: Documentation, https://github.com/kedro-org/kedro-plugins/blob/main/kedro-docker/README.md
Project-URL: Tracker, https://github.com/kedro-org/kedro-plugins/issues
Requires-Python: >=3.9
Requires-Dist: anyconfig~=0.10.0
Requires-Dist: kedro>=0.16.0
Requires-Dist: semver~=2.10
Provides-Extra: test
Requires-Dist: behave; extra == "test"
Requires-Dist: coverage>=7.2.0; extra == "test"
Requires-Dist: docker; extra == "test"
Requires-Dist: psutil; extra == "test"
Requires-Dist: pytest; extra == "test"
Requires-Dist: pytest-cov; extra == "test"
Requires-Dist: pytest-mock; extra == "test"
Requires-Dist: pytest-xdist[psutil]~=2.2.1; extra == "test"
Requires-Dist: PyYAML<7.0,>=5.1; extra == "test"
Requires-Dist: wheel==0.32.2; extra == "test"
Provides-Extra: lint
Requires-Dist: bandit; extra == "lint"
Requires-Dist: black~=22.0; extra == "lint"
Requires-Dist: mypy~=1.0; extra == "lint"
Requires-Dist: pre-commit>=2.9.2; extra == "lint"
Requires-Dist: trufflehog<3.0,>=2.1.0; extra == "lint"
Requires-Dist: ruff~=0.0.290; extra == "lint"
